GameserverLister/__init__.py
GameserverLister/__main__.py
GameserverLister/commands/__init__.py
GameserverLister/commands/battlelog.py
GameserverLister/commands/bfbc2.py
GameserverLister/commands/gamespy.py
GameserverLister/commands/gametools.py
GameserverLister/commands/medalofhonor.py
GameserverLister/commands/quake3.py
GameserverLister/commands/unreal2.py
GameserverLister/commands/valve.py
GameserverLister/commands/options/__init__.py
GameserverLister/commands/options/common.py
GameserverLister/commands/options/gameport.py
GameserverLister/commands/options/http.py
GameserverLister/commands/options/queryport.py
GameserverLister/common/__init__.py
GameserverLister/common/constants.py
GameserverLister/common/helpers.py
GameserverLister/common/logger.py
GameserverLister/common/servers.py
GameserverLister/common/types.py
GameserverLister/common/weblinks.py
GameserverLister/games/__init__.py
GameserverLister/games/battlelog.py
GameserverLister/games/gamespy.py
GameserverLister/games/gametools.py
GameserverLister/games/quake3.py
GameserverLister/games/unreal2.py
GameserverLister/games/valve.py
GameserverLister/listers/__init__.py
GameserverLister/listers/battlelog.py
GameserverLister/listers/bfbc2.py
GameserverLister/listers/common.py
GameserverLister/listers/gamespy.py
GameserverLister/listers/gametools.py
GameserverLister/listers/medalofhonor.py
GameserverLister/listers/quake3.py
GameserverLister/listers/unreal2.py
GameserverLister/listers/valve.py
GameserverLister-2.2.1.dist-info/LICENSE.md
GameserverLister-2.2.1.dist-info/METADATA
GameserverLister-2.2.1.dist-info/WHEEL
GameserverLister-2.2.1.dist-info/entry_points.txt
GameserverLister-2.2.1.dist-info/top_level.txt
GameserverLister-2.2.1.dist-info/RECORD
