Metadata-Version: 2.1
Name: GameserverLister
Version: 2.2.1
Summary: Python command line tool to retrieve game server lists for various games
Home-page: https://github.com/cetteup/GameserverLister
Author: cetteup
Author-email: me@cetteup.com
License: MIT
Project-URL: Bug Tracker, https://github.com/cetteup/GameserverLister/issues
Classifier: Development Status :: 5 - Production/Stable
Classifier: Environment :: Console
Classifier: Intended Audience :: Developers
Classifier: Intended Audience :: Other Audience
Classifier: Intended Audience :: System Administrators
Classifier: License :: OSI Approved :: MIT License
Classifier: Natural Language :: English
Classifier: Operating System :: Microsoft :: Windows
Classifier: Operating System :: POSIX :: Linux
Classifier: Programming Language :: Python :: 3
Classifier: Programming Language :: Python :: 3 :: Only
Classifier: Programming Language :: Python :: 3.8
Classifier: Programming Language :: Python :: 3.9
Classifier: Programming Language :: Python :: 3.10
Classifier: Programming Language :: Python :: 3.11
Classifier: Topic :: Games/Entertainment
Classifier: Topic :: Internet
Requires-Python: <3.12,>=3.8
License-File: LICENSE.md
Requires-Dist: gevent==24.2.1
Requires-Dist: nslookup==1.8.1
Requires-Dist: requests[socks]==2.32.3
Requires-Dist: pyq3serverlist==0.3.2
Requires-Dist: pyut2serverlist==0.2.0
Requires-Dist: pyvpsq==0.1.2
Requires-Dist: click==8.1.7
